{
    "produtos": [
        {
            "id": "4dd2eacf-9319-4a1c-8602-3f67721ec792",
            "name": "banana"
        },
        {
            "id": "7e9cd008-f713-47b1-b40b-0d30a8710189",
            "name": "maçã"
        },
        {
            "id": "ed129dcf-66f0-40bd-b546-eafb986223cd",
            "name": "batata"
        }
    ],
    "entradas": [
        {
            "id": "269d4072-015d-4a79-9e9d-e57b046a2b7e",
            "nf": "1111",
            "createdAt": "2022-05-11T10:30:40.745977",
            "produtos": [
                {
                    "produto": {
                        "id": "6b8f9c61-c5a6-442c-b67d-71c6b6674f8c",
                        "name": "banana"
                    },
                    "quantidade": 10
                },
                {
                    "produto": {
                        "id": "1cf6ad40-e7d8-4b84-9857-9872bf73a81e",
                        "name": "morango"
                    },
                    "quantidade": 10
                },
                {
                    "produto": {
                        "id": "068e4981-536a-4797-bab9-1ef9b98596fc",
                        "name": "melancia"
                    },
                    "quantidade": 20
                }
            ]
        },
        {
            "id": "cbf7d578-f0b7-4f2b-804f-cb19615c3e20",
            "nf": "1222",
            "createdAt": "2022-05-11T10:30:40.745977",
            "produtos": [
                {
                    "produto": {
                        "id": "e35210ec-ca2a-4b72-8164-30db0ba4ef4c",
                        "name": "beterraba"
                    },
                    "quantidade": 20
                },
                {
                    "produto": {
                        "id": "b47beaad-4b09-4e1b-bd92-8f0763255647",
                        "name": "tanja"
                    },
                    "quantidade": 40
                },
                {
                    "produto": {
                        "id": "6b8f9c61-c5a6-442c-b67d-71c6b6674f8c",
                        "name": "banana"
                    },
                    "quantidade": 50
                }
            ]
        }
    ],
    "saidas": [
        {
            "id": "2f94dfd6-006d-444e-990a-06971ce2e8b3",
            "nf": "1133",
            "createdAt": "2022-05-11T10:30:53.165066",
            "produtos": [
                {
                    "produto": {
                        "id": "4dd2eacf-9319-4a1c-8602-3f67721ec792",
                        "name": "banana"
                    },
                    "quantidade": 5
                }
            ]
        }
    ]
}